ronen_sqlalchemy/__init__.py
ronen_sqlalchemy/ddl.py
ronen_sqlalchemy/main.py
ronen_sqlalchemy-0.1.2.dist-info/LICENSE
ronen_sqlalchemy-0.1.2.dist-info/METADATA
ronen_sqlalchemy-0.1.2.dist-info/WHEEL
ronen_sqlalchemy-0.1.2.dist-info/entry_points.txt
ronen_sqlalchemy-0.1.2.dist-info/RECORD
