Metadata-Version: 2.1
Name: ronen-sqlalchemy
Version: 0.1.2
Summary: Load sqlalchemy models into an Atlas project.
Author: Your Name
Author-email: you@example.com
Requires-Python: >=3.8,<4.0
Classifier: Programming Language :: Python :: 3
Classifier: Programming Language :: Python :: 3.8
Classifier: Programming Language :: Python :: 3.9
Classifier: Programming Language :: Python :: 3.10
Classifier: Programming Language :: Python :: 3.11
Classifier: Programming Language :: Python :: 3.12
Requires-Dist: sqlalchemy (>=2.0.21,<3.0.0)
Requires-Dist: typer[all] (>=0.9.0,<0.10.0)
